postcard/__init__.py
postcard/imap.py
postcard/pop3.py
postcard/run.py
postcard/setting.py
postcard/smtp.py
postcard-0.3.2.dist-info/LICENSE
postcard-0.3.2.dist-info/METADATA
postcard-0.3.2.dist-info/WHEEL
postcard-0.3.2.dist-info/entry_points.txt
postcard-0.3.2.dist-info/top_level.txt
postcard-0.3.2.dist-info/RECORD
