Metadata-Version: 2.1
Name: postcard
Version: 0.3.2
Summary: A POP3/IMAP/SMTP client.
Home-page: https://leesoar.com
Author: leesoar
Author-email: secure@tom.com
License: MIT
Keywords: mail,email,postal,postcard,mailbox,postbox
Platform: UNKNOWN
Classifier: License :: OSI Approved :: MIT License
Classifier: Programming Language :: Python :: 3.5
Classifier: Programming Language :: Python :: 3.6
Classifier: Programming Language :: Python :: 3.7
Classifier: Programming Language :: Python :: Implementation :: CPython
Classifier: Programming Language :: Python :: Implementation :: PyPy
Requires-Python: >=3.3.0
